CHANGELOG.md
LICENSE
MANIFEST.in
README.md
requirements.txt
setup.py
appstoreconnect/__init__.py
appstoreconnect/__version__.py
appstoreconnect/api.py
appstoreconnect/resources.py
appstoreconnect.egg-info/PKG-INFO
appstoreconnect.egg-info/SOURCES.txt
appstoreconnect.egg-info/dependency_links.txt
appstoreconnect.egg-info/requires.txt
appstoreconnect.egg-info/top_level.txt