Metadata-Version: 2.1
Name: appstoreconnect
Version: 0.3.0
Summary: A Python wrapper around Apple App Store Api
Home-page: https://github.com/ponytech/appstoreconnectapi
Author: Ponytech
Author-email: contact@ponytech.net
License: MIT
Platform: UNKNOWN
Classifier: License :: OSI Approved :: MIT License
Classifier: Programming Language :: Python
Classifier: Programming Language :: Python :: 3
Classifier: Programming Language :: Python :: 3.6
Classifier: Programming Language :: Python :: 3.7
Requires-Python: >=3.6.0
